[
    {
        "catagory_id": "6357f0ceaf523537ee66271c",
        "course_id": "6357f0cee7d72dd1ab0e5758",
        "title": "Mullen Sawyer",
        "Instructor": "Hays Klein",
        "description": 0,
        "picture": "http://placehold.it/32x32"
    },
    {
        "catagory_id": "6357f0ce0bd76a3eb1681b0e",
        "course_id": "6357f0ce58dad1c58e45fc91",
        "title": "Robyn Shaw",
        "Instructor": "Walters Norton",
        "description": 1,
        "picture": "http://placehold.it/32x32"
    },
    {
        "catagory_id": "6357f0cead623b73e2012d04",
        "course_id": "6357f0ceb34b73c7c5b4bdd2",
        "title": "Jody Hunt",
        "Instructor": "Carr Sears",
        "description": 2,
        "picture": "http://placehold.it/32x32"
    },
    {
        "catagory_id": "6357f0cea9b5b974ba1cb8b8",
        "course_id": "6357f0ce166d44261f7e52ca",
        "title": "Ines Jacobson",
        "Instructor": "Iva Velazquez",
        "description": 3,
        "picture": "http://placehold.it/32x32"
    },
    {
        "catagory_id": "6357f0cee766d07a749fb738",
        "course_id": "6357f0ce394ffeffc55fb8ad",
        "title": "Dionne Hull",
        "Instructor": "Parrish Page",
        "description": 4,
        "picture": "http://placehold.it/32x32"
    },
    {
        "catagory_id": "6357f0ce25bd4c5c9c2a716e",
        "course_id": "6357f0cead5ccf7419bee53c",
        "title": "Anne Sosa",
        "Instructor": "Henry Mathis",
        "description": 5,
        "picture": "http://placehold.it/32x32"
    }
]